{
  "Subject search - African" : {
    "transaction" : "Subject search - African",
    "sampleCount" : 627,
    "errorCount" : 0,
    "errorPct" : 0.0,
    "meanResTime" : 3912.574162679427,
    "minResTime" : 1851.0,
    "maxResTime" : 9559.0,
    "pct1ResTime" : 5312.000000000001,
    "pct2ResTime" : 5623.200000000001,
    "pct3ResTime" : 7310.600000000006,
    "throughput" : 0.6975083267142352,
    "receivedKBytesPerSec" : 1082.2781527470231,
    "sentKBytesPerSec" : 1.713310884717559
  },
  "load item page-5" : {
    "transaction" : "load item page-5",
    "sampleCount" : 619,
    "errorCount" : 0,
    "errorPct" : 0.0,
    "meanResTime" : 268.0743134087238,
    "minResTime" : 53.0,
    "maxResTime" : 2867.0,
    "pct1ResTime" : 482.0,
    "pct2ResTime" : 556.0,
    "pct3ResTime" : 961.7999999999993,
    "throughput" : 0.7013862292615163,
    "receivedKBytesPerSec" : 6.463130208345136,
    "sentKBytesPerSec" : 0.40343407132327447
  },
  "load item page-4" : {
    "transaction" : "load item page-4",
    "sampleCount" : 619,
    "errorCount" : 0,
    "errorPct" : 0.0,
    "meanResTime" : 308.0032310177708,
    "minResTime" : 65.0,
    "maxResTime" : 3026.0,
    "pct1ResTime" : 524.0,
    "pct2ResTime" : 620.0,
    "pct3ResTime" : 1016.9999999999966,
    "throughput" : 0.7013218614147214,
    "receivedKBytesPerSec" : 14.859182807431631,
    "sentKBytesPerSec" : 0.40887612428182485
  },
  "load item page-3" : {
    "transaction" : "load item page-3",
    "sampleCount" : 619,
    "errorCount" : 0,
    "errorPct" : 0.0,
    "meanResTime" : 219.6720516962843,
    "minResTime" : 30.0,
    "maxResTime" : 1978.0,
    "pct1ResTime" : 439.0,
    "pct2ResTime" : 551.0,
    "pct3ResTime" : 834.7999999999984,
    "throughput" : 0.7015094352452392,
    "receivedKBytesPerSec" : 0.6842565724719311,
    "sentKBytesPerSec" : 0.43775832922041785
  },
  "Subject search - African-3" : {
    "transaction" : "Subject search - African-3",
    "sampleCount" : 627,
    "errorCount" : 0,
    "errorPct" : 0.0,
    "meanResTime" : 193.03349282296656,
    "minResTime" : 25.0,
    "maxResTime" : 1101.0,
    "pct1ResTime" : 306.20000000000005,
    "pct2ResTime" : 486.60000000000014,
    "pct3ResTime" : 690.840000000002,
    "throughput" : 0.6997736617247244,
    "receivedKBytesPerSec" : 0.6825411162366463,
    "sentKBytesPerSec" : 0.43667516586142474
  },
  "load item page-2" : {
    "transaction" : "load item page-2",
    "sampleCount" : 619,
    "errorCount" : 0,
    "errorPct" : 0.0,
    "meanResTime" : 3644.3586429725356,
    "minResTime" : 696.0,
    "maxResTime" : 7320.0,
    "pct1ResTime" : 5044.0,
    "pct2ResTime" : 5435.0,
    "pct3ResTime" : 6693.999999999997,
    "throughput" : 0.6986156349953389,
    "receivedKBytesPerSec" : 838.3760946200953,
    "sentKBytesPerSec" : 0.43731701370313686
  },
  "Subject search - African-2" : {
    "transaction" : "Subject search - African-2",
    "sampleCount" : 627,
    "errorCount" : 0,
    "errorPct" : 0.0,
    "meanResTime" : 3590.609250398722,
    "minResTime" : 683.0,
    "maxResTime" : 9127.0,
    "pct1ResTime" : 4944.2,
    "pct2ResTime" : 5297.0,
    "pct3ResTime" : 6870.560000000007,
    "throughput" : 0.6977699184377076,
    "receivedKBytesPerSec" : 837.3611593838091,
    "sentKBytesPerSec" : 0.4367876149595416
  },
  "load item page-1" : {
    "transaction" : "load item page-1",
    "sampleCount" : 619,
    "errorCount" : 0,
    "errorPct" : 0.0,
    "meanResTime" : 1397.953150242324,
    "minResTime" : 264.0,
    "maxResTime" : 4085.0,
    "pct1ResTime" : 1997.0,
    "pct2ResTime" : 2283.0,
    "pct3ResTime" : 3227.599999999996,
    "throughput" : 0.7004306686793204,
    "receivedKBytesPerSec" : 237.6324695955522,
    "sentKBytesPerSec" : 0.4391371965743396
  },
  "Subject search - African-1" : {
    "transaction" : "Subject search - African-1",
    "sampleCount" : 627,
    "errorCount" : 0,
    "errorPct" : 0.0,
    "meanResTime" : 1348.6953748006388,
    "minResTime" : 218.0,
    "maxResTime" : 4056.0,
    "pct1ResTime" : 1860.2,
    "pct2ResTime" : 2148.4,
    "pct3ResTime" : 2969.0800000000017,
    "throughput" : 0.6987715217728068,
    "receivedKBytesPerSec" : 237.06951948626642,
    "sentKBytesPerSec" : 0.4380969892364667
  },
  "load item page-0" : {
    "transaction" : "load item page-0",
    "sampleCount" : 619,
    "errorCount" : 0,
    "errorPct" : 0.0,
    "meanResTime" : 473.0710823909533,
    "minResTime" : 222.0,
    "maxResTime" : 3294.0,
    "pct1ResTime" : 643.0,
    "pct2ResTime" : 775.0,
    "pct3ResTime" : 1440.1999999999994,
    "throughput" : 0.7002745664576402,
    "receivedKBytesPerSec" : 18.34732488964171,
    "sentKBytesPerSec" : 0.3952721673950352
  },
  "Subject search - African-0" : {
    "transaction" : "Subject search - African-0",
    "sampleCount" : 627,
    "errorCount" : 0,
    "errorPct" : 0.0,
    "meanResTime" : 317.33173843700155,
    "minResTime" : 84.0,
    "maxResTime" : 1528.0,
    "pct1ResTime" : 515.4000000000001,
    "pct2ResTime" : 632.6,
    "pct3ResTime" : 1237.2400000000005,
    "throughput" : 0.6995519297368703,
    "receivedKBytesPerSec" : 7.932799772157498,
    "sentKBytesPerSec" : 0.4053044682624335
  },
  "Home page-0" : {
    "transaction" : "Home page-0",
    "sampleCount" : 631,
    "errorCount" : 0,
    "errorPct" : 0.0,
    "meanResTime" : 396.1125198098259,
    "minResTime" : 101.0,
    "maxResTime" : 4559.0,
    "pct1ResTime" : 564.0000000000003,
    "pct2ResTime" : 738.1999999999999,
    "pct3ResTime" : 1554.8799999999978,
    "throughput" : 0.7009109620919359,
    "receivedKBytesPerSec" : 13.052633425094168,
    "sentKBytesPerSec" : 0.3729891939884944
  },
  "Home page-2" : {
    "transaction" : "Home page-2",
    "sampleCount" : 631,
    "errorCount" : 1,
    "errorPct" : 0.1584786,
    "meanResTime" : 3638.8716323296358,
    "minResTime" : 1.0,
    "maxResTime" : 10276.0,
    "pct1ResTime" : 5013.800000000001,
    "pct2ResTime" : 5499.599999999999,
    "pct3ResTime" : 7062.919999999998,
    "throughput" : 0.6991434108226513,
    "receivedKBytesPerSec" : 837.6820973062758,
    "sentKBytesPerSec" : 0.4351360109547241
  },
  "Home page-1" : {
    "transaction" : "Home page-1",
    "sampleCount" : 631,
    "errorCount" : 0,
    "errorPct" : 0.0,
    "meanResTime" : 1445.9413629160053,
    "minResTime" : 290.0,
    "maxResTime" : 4569.0,
    "pct1ResTime" : 2001.4000000000005,
    "pct2ResTime" : 2236.0,
    "pct3ResTime" : 3619.7599999999948,
    "throughput" : 0.6999429840421875,
    "receivedKBytesPerSec" : 237.4670045015846,
    "sentKBytesPerSec" : 0.43701156167706784
  },
  "Home page-4" : {
    "transaction" : "Home page-4",
    "sampleCount" : 631,
    "errorCount" : 0,
    "errorPct" : 0.0,
    "meanResTime" : 440.29952456418374,
    "minResTime" : 158.0,
    "maxResTime" : 2772.0,
    "pct1ResTime" : 765.8000000000001,
    "pct2ResTime" : 973.5999999999997,
    "pct3ResTime" : 1339.3999999999996,
    "throughput" : 0.7010706048094999,
    "receivedKBytesPerSec" : 108.16322539558826,
    "sentKBytesPerSec" : 0.1328200169267998
  },
  "Home page-3" : {
    "transaction" : "Home page-3",
    "sampleCount" : 631,
    "errorCount" : 0,
    "errorPct" : 0.0,
    "meanResTime" : 226.07448494453237,
    "minResTime" : 27.0,
    "maxResTime" : 1824.0,
    "pct1ResTime" : 430.60000000000014,
    "pct2ResTime" : 524.5999999999998,
    "pct3ResTime" : 971.4799999999907,
    "throughput" : 0.7009646873764147,
    "receivedKBytesPerSec" : 0.68372328023424,
    "sentKBytesPerSec" : 0.43559585782358795
  },
  "Home page-6" : {
    "transaction" : "Home page-6",
    "sampleCount" : 631,
    "errorCount" : 1,
    "errorPct" : 0.1584786,
    "meanResTime" : 285.9096671949285,
    "minResTime" : 1.0,
    "maxResTime" : 2946.0,
    "pct1ResTime" : 511.2000000000003,
    "pct2ResTime" : 593.0,
    "pct3ResTime" : 1068.639999999999,
    "throughput" : 0.7012131765845918,
    "receivedKBytesPerSec" : 5.923316598721591,
    "sentKBytesPerSec" : 0.4008721512520156
  },
  "Home page" : {
    "transaction" : "Home page",
    "sampleCount" : 631,
    "errorCount" : 2,
    "errorPct" : 0.3169572,
    "meanResTime" : 4050.0269413629185,
    "minResTime" : 1327.0,
    "maxResTime" : 10747.0,
    "pct1ResTime" : 5497.800000000001,
    "pct2ResTime" : 6098.2,
    "pct3ResTime" : 7350.199999999999,
    "throughput" : 0.6986897629216083,
    "receivedKBytesPerSec" : 1327.8148443927378,
    "sentKBytesPerSec" : 5.408765388683551
  },
  "Home page-5" : {
    "transaction" : "Home page-5",
    "sampleCount" : 631,
    "errorCount" : 0,
    "errorPct" : 0.0,
    "meanResTime" : 428.75752773375615,
    "minResTime" : 140.0,
    "maxResTime" : 3957.0,
    "pct1ResTime" : 644.8000000000001,
    "pct2ResTime" : 804.3999999999999,
    "pct3ResTime" : 1510.759999999996,
    "throughput" : 0.7011227964910527,
    "receivedKBytesPerSec" : 25.06666343744618,
    "sentKBytesPerSec" : 0.4014595989794274
  },
  "Open search" : {
    "transaction" : "Open search",
    "sampleCount" : 630,
    "errorCount" : 1,
    "errorPct" : 0.15873016,
    "meanResTime" : 4460.50476190476,
    "minResTime" : 1367.0,
    "maxResTime" : 9317.0,
    "pct1ResTime" : 5773.7,
    "pct2ResTime" : 6387.499999999998,
    "pct3ResTime" : 7857.289999999997,
    "throughput" : 0.6995118961435798,
    "receivedKBytesPerSec" : 1312.982976791611,
    "sentKBytesPerSec" : 5.740252391942067
  },
  "Home page-8" : {
    "transaction" : "Home page-8",
    "sampleCount" : 631,
    "errorCount" : 0,
    "errorPct" : 0.0,
    "meanResTime" : 420.91759112519793,
    "minResTime" : 128.0,
    "maxResTime" : 3294.0,
    "pct1ResTime" : 636.8000000000001,
    "pct2ResTime" : 763.1999999999999,
    "pct3ResTime" : 1435.2799999999988,
    "throughput" : 0.7013254049848564,
    "receivedKBytesPerSec" : 22.630972093903694,
    "sentKBytesPerSec" : 0.40157561164522493
  },
  "Home page-7" : {
    "transaction" : "Home page-7",
    "sampleCount" : 631,
    "errorCount" : 0,
    "errorPct" : 0.0,
    "meanResTime" : 351.38034865293173,
    "minResTime" : 156.0,
    "maxResTime" : 3052.0,
    "pct1ResTime" : 543.4000000000002,
    "pct2ResTime" : 659.3999999999995,
    "pct3ResTime" : 1350.1199999999983,
    "throughput" : 0.7012357752489331,
    "receivedKBytesPerSec" : 12.981995410295163,
    "sentKBytesPerSec" : 0.4015242900821257
  },
  "Home page-9" : {
    "transaction" : "Home page-9",
    "sampleCount" : 631,
    "errorCount" : 0,
    "errorPct" : 0.0,
    "meanResTime" : 254.07448494453237,
    "minResTime" : 45.0,
    "maxResTime" : 2972.0,
    "pct1ResTime" : 410.80000000000007,
    "pct2ResTime" : 538.5999999999997,
    "pct3ResTime" : 1196.0799999999986,
    "throughput" : 0.701399464224181,
    "receivedKBytesPerSec" : 6.461384645632093,
    "sentKBytesPerSec" : 0.4016180176155753
  },
  "Open search-4" : {
    "transaction" : "Open search-4",
    "sampleCount" : 630,
    "errorCount" : 0,
    "errorPct" : 0.0,
    "meanResTime" : 412.4730158730166,
    "minResTime" : 101.0,
    "maxResTime" : 5513.0,
    "pct1ResTime" : 655.9,
    "pct2ResTime" : 793.8999999999999,
    "pct3ResTime" : 1329.389999999998,
    "throughput" : 0.701842727071188,
    "receivedKBytesPerSec" : 22.648941966866897,
    "sentKBytesPerSec" : 0.40320708008916745
  },
  "Open search-3" : {
    "transaction" : "Open search-3",
    "sampleCount" : 630,
    "errorCount" : 0,
    "errorPct" : 0.0,
    "meanResTime" : 204.48253968253985,
    "minResTime" : 29.0,
    "maxResTime" : 1725.0,
    "pct1ResTime" : 337.5999999999999,
    "pct2ResTime" : 464.1499999999995,
    "pct3ResTime" : 636.0699999999998,
    "throughput" : 0.7021947486978746,
    "receivedKBytesPerSec" : 0.6849315903485004,
    "sentKBytesPerSec" : 0.4376961686916997
  },
  "Open search-6" : {
    "transaction" : "Open search-6",
    "sampleCount" : 630,
    "errorCount" : 0,
    "errorPct" : 0.0,
    "meanResTime" : 292.9396825396822,
    "minResTime" : 50.0,
    "maxResTime" : 3394.0,
    "pct1ResTime" : 489.9,
    "pct2ResTime" : 674.799999999997,
    "pct3ResTime" : 1372.4499999999998,
    "throughput" : 0.7021430967631204,
    "receivedKBytesPerSec" : 7.743633118947498,
    "sentKBytesPerSec" : 0.4033796418067145
  },
  "Open search-5" : {
    "transaction" : "Open search-5",
    "sampleCount" : 630,
    "errorCount" : 0,
    "errorPct" : 0.0,
    "meanResTime" : 273.81428571428563,
    "minResTime" : 50.0,
    "maxResTime" : 1720.0,
    "pct1ResTime" : 477.9,
    "pct2ResTime" : 585.4499999999999,
    "pct3ResTime" : 1184.6399999999908,
    "throughput" : 0.7021415316715983,
    "receivedKBytesPerSec" : 6.469600989615549,
    "sentKBytesPerSec" : 0.40337874266512863
  },
  "Open search-0" : {
    "transaction" : "Open search-0",
    "sampleCount" : 630,
    "errorCount" : 0,
    "errorPct" : 0.0,
    "meanResTime" : 743.4587301587301,
    "minResTime" : 337.0,
    "maxResTime" : 2707.0,
    "pct1ResTime" : 968.6999999999999,
    "pct2ResTime" : 1095.3999999999992,
    "pct3ResTime" : 1573.2799999999993,
    "throughput" : 0.7020280811232449,
    "receivedKBytesPerSec" : 43.730697274765994,
    "sentKBytesPerSec" : 0.4122586778471139
  },
  "Open search-2" : {
    "transaction" : "Open search-2",
    "sampleCount" : 630,
    "errorCount" : 0,
    "errorPct" : 0.0,
    "meanResTime" : 3678.55396825397,
    "minResTime" : 424.0,
    "maxResTime" : 8653.0,
    "pct1ResTime" : 5040.2,
    "pct2ResTime" : 5560.649999999996,
    "pct3ResTime" : 7115.939999999999,
    "throughput" : 0.6997799580798482,
    "receivedKBytesPerSec" : 839.7733511295893,
    "sentKBytesPerSec" : 0.4375577249042801
  },
  "Open search-1" : {
    "transaction" : "Open search-1",
    "sampleCount" : 630,
    "errorCount" : 1,
    "errorPct" : 0.15873016,
    "meanResTime" : 1484.0507936507927,
    "minResTime" : 0.0,
    "maxResTime" : 4193.0,
    "pct1ResTime" : 2229.8999999999996,
    "pct2ResTime" : 2572.7999999999997,
    "pct3ResTime" : 3229.039999999999,
    "throughput" : 0.701147544815014,
    "receivedKBytesPerSec" : 237.5004506072856,
    "sentKBytesPerSec" : 0.43839980601584594
  },
  "facet English language-13" : {
    "transaction" : "facet English language-13",
    "sampleCount" : 622,
    "errorCount" : 0,
    "errorPct" : 0.0,
    "meanResTime" : 116.26688102893901,
    "minResTime" : 45.0,
    "maxResTime" : 2464.0,
    "pct1ResTime" : 160.10000000000014,
    "pct2ResTime" : 237.0,
    "pct3ResTime" : 1071.6799999999967,
    "throughput" : 0.701882670494297,
    "receivedKBytesPerSec" : 4.782991738561682,
    "sentKBytesPerSec" : 0.40371962199330164
  },
  "facet English language-11" : {
    "transaction" : "facet English language-11",
    "sampleCount" : 622,
    "errorCount" : 0,
    "errorPct" : 0.0,
    "meanResTime" : 150.05787781350506,
    "minResTime" : 44.0,
    "maxResTime" : 2431.0,
    "pct1ResTime" : 227.70000000000005,
    "pct2ResTime" : 312.75000000000034,
    "pct3ResTime" : 1135.4199999999955,
    "throughput" : 0.7015842042038655,
    "receivedKBytesPerSec" : 8.847265323185553,
    "sentKBytesPerSec" : 0.4035479455821062
  },
  "facet English language-12" : {
    "transaction" : "facet English language-12",
    "sampleCount" : 622,
    "errorCount" : 0,
    "errorPct" : 0.0,
    "meanResTime" : 126.33601286173631,
    "minResTime" : 45.0,
    "maxResTime" : 2624.0,
    "pct1ResTime" : 206.4000000000001,
    "pct2ResTime" : 289.10000000000014,
    "pct3ResTime" : 1067.6099999999983,
    "throughput" : 0.7016008229709975,
    "receivedKBytesPerSec" : 7.865671271674051,
    "sentKBytesPerSec" : 0.4035575046190601
  },
  "Open search-8" : {
    "transaction" : "Open search-8",
    "sampleCount" : 630,
    "errorCount" : 0,
    "errorPct" : 0.0,
    "meanResTime" : 299.29682539682517,
    "minResTime" : 66.0,
    "maxResTime" : 1678.0,
    "pct1ResTime" : 530.8,
    "pct2ResTime" : 645.0499999999994,
    "pct3ResTime" : 1284.4499999999998,
    "throughput" : 0.7021204036189291,
    "receivedKBytesPerSec" : 8.951530148827235,
    "sentKBytesPerSec" : 0.40336660464603097
  },
  "Open search-7" : {
    "transaction" : "Open search-7",
    "sampleCount" : 630,
    "errorCount" : 0,
    "errorPct" : 0.0,
    "meanResTime" : 282.23968253968275,
    "minResTime" : 116.0,
    "maxResTime" : 1490.0,
    "pct1ResTime" : 481.4999999999999,
    "pct2ResTime" : 622.8999999999999,
    "pct3ResTime" : 1284.69,
    "throughput" : 0.7021783131670695,
    "receivedKBytesPerSec" : 7.96415754136722,
    "sentKBytesPerSec" : 0.4033998735521752
  },
  "facet English language" : {
    "transaction" : "facet English language",
    "sampleCount" : 623,
    "errorCount" : 1,
    "errorPct" : 0.16051364,
    "meanResTime" : 4442.412520064202,
    "minResTime" : 1.0,
    "maxResTime" : 8761.0,
    "pct1ResTime" : 5725.400000000001,
    "pct2ResTime" : 6154.799999999999,
    "pct3ResTime" : 8030.5999999999985,
    "throughput" : 0.6966420288720662,
    "receivedKBytesPerSec" : 1215.0999096961696,
    "sentKBytesPerSec" : 5.73603387533686
  },
  "facet English language-10" : {
    "transaction" : "facet English language-10",
    "sampleCount" : 622,
    "errorCount" : 0,
    "errorPct" : 0.0,
    "meanResTime" : 242.64147909967852,
    "minResTime" : 42.0,
    "maxResTime" : 2877.0,
    "pct1ResTime" : 455.60000000000036,
    "pct2ResTime" : 565.0,
    "pct3ResTime" : 1226.6799999999985,
    "throughput" : 0.7015818301585439,
    "receivedKBytesPerSec" : 7.513743261585688,
    "sentKBytesPerSec" : 0.4035465800423656
  },
  "Open search-9" : {
    "transaction" : "Open search-9",
    "sampleCount" : 630,
    "errorCount" : 0,
    "errorPct" : 0.0,
    "meanResTime" : 497.66507936507924,
    "minResTime" : 151.0,
    "maxResTime" : 2184.0,
    "pct1ResTime" : 774.3999999999996,
    "pct2ResTime" : 937.5499999999987,
    "pct3ResTime" : 1468.459999999998,
    "throughput" : 0.7021970966936548,
    "receivedKBytesPerSec" : 34.92825581555734,
    "sentKBytesPerSec" : 0.403410664646271
  },
  "Home page-10" : {
    "transaction" : "Home page-10",
    "sampleCount" : 631,
    "errorCount" : 1,
    "errorPct" : 0.1584786,
    "meanResTime" : 226.03961965134715,
    "minResTime" : 44.0,
    "maxResTime" : 2518.0,
    "pct1ResTime" : 386.40000000000055,
    "pct2ResTime" : 548.3999999999997,
    "pct3ResTime" : 1036.4399999999996,
    "throughput" : 0.7015382699688254,
    "receivedKBytesPerSec" : 7.725491726490129,
    "sentKBytesPerSec" : 0.4010580018444564
  },
  "Home page-11" : {
    "transaction" : "Home page-11",
    "sampleCount" : 631,
    "errorCount" : 0,
    "errorPct" : 0.0,
    "meanResTime" : 140.97464342313782,
    "minResTime" : 43.0,
    "maxResTime" : 2354.0,
    "pct1ResTime" : 241.0,
    "pct2ResTime" : 366.5999999999999,
    "pct3ResTime" : 775.0799999999947,
    "throughput" : 0.7015491896050645,
    "receivedKBytesPerSec" : 7.955144412052304,
    "sentKBytesPerSec" : 0.4017037496608994
  },
  "load item page" : {
    "transaction" : "load item page",
    "sampleCount" : 619,
    "errorCount" : 0,
    "errorPct" : 0.0,
    "meanResTime" : 4126.159935379647,
    "minResTime" : 2072.0,
    "maxResTime" : 8996.0,
    "pct1ResTime" : 5516.0,
    "pct2ResTime" : 5982.0,
    "pct3ResTime" : 7258.399999999996,
    "throughput" : 0.6973225742130338,
    "receivedKBytesPerSec" : 1113.5526383140452,
    "sentKBytesPerSec" : 2.5100888755363693
  },
  "Home page-12" : {
    "transaction" : "Home page-12",
    "sampleCount" : 631,
    "errorCount" : 0,
    "errorPct" : 0.0,
    "meanResTime" : 264.11568938193307,
    "minResTime" : 93.0,
    "maxResTime" : 1730.0,
    "pct1ResTime" : 389.80000000000007,
    "pct2ResTime" : 482.9999999999998,
    "pct3ResTime" : 1057.7599999999998,
    "throughput" : 0.7012326581051826,
    "receivedKBytesPerSec" : 29.091160089276585,
    "sentKBytesPerSec" : 0.40152250522034927
  },
  "Home page-13" : {
    "transaction" : "Home page-13",
    "sampleCount" : 631,
    "errorCount" : 0,
    "errorPct" : 0.0,
    "meanResTime" : 184.5039619651346,
    "minResTime" : 77.0,
    "maxResTime" : 1263.0,
    "pct1ResTime" : 257.80000000000007,
    "pct2ResTime" : 376.79999999999984,
    "pct3ResTime" : 906.8399999999981,
    "throughput" : 0.7015476296362181,
    "receivedKBytesPerSec" : 14.804697923152183,
    "sentKBytesPerSec" : 0.40170285643011205
  },
  "facet English language-8" : {
    "transaction" : "facet English language-8",
    "sampleCount" : 622,
    "errorCount" : 0,
    "errorPct" : 0.0,
    "meanResTime" : 357.26848874598085,
    "minResTime" : 101.0,
    "maxResTime" : 3063.0,
    "pct1ResTime" : 550.8000000000002,
    "pct2ResTime" : 770.7500000000003,
    "pct3ResTime" : 1405.0299999999993,
    "throughput" : 0.7012962706146715,
    "receivedKBytesPerSec" : 14.801863676165173,
    "sentKBytesPerSec" : 0.40338232753129055
  },
  "facet English language-9" : {
    "transaction" : "facet English language-9",
    "sampleCount" : 622,
    "errorCount" : 0,
    "errorPct" : 0.0,
    "meanResTime" : 427.8778135048234,
    "minResTime" : 136.0,
    "maxResTime" : 3189.0,
    "pct1ResTime" : 684.1000000000001,
    "pct2ResTime" : 802.5000000000002,
    "pct3ResTime" : 1409.62,
    "throughput" : 0.7010923289002206,
    "receivedKBytesPerSec" : 24.701143279968033,
    "sentKBytesPerSec" : 0.40326502121311514
  },
  "facet English language-4" : {
    "transaction" : "facet English language-4",
    "sampleCount" : 622,
    "errorCount" : 0,
    "errorPct" : 0.0,
    "meanResTime" : 285.096463022508,
    "minResTime" : 45.0,
    "maxResTime" : 2243.0,
    "pct1ResTime" : 509.8000000000002,
    "pct2ResTime" : 658.5000000000002,
    "pct3ResTime" : 1529.1599999999999,
    "throughput" : 0.7007566369089197,
    "receivedKBytesPerSec" : 6.4572925022419705,
    "sentKBytesPerSec" : 0.4030719327532751
  },
  "facet English language-5" : {
    "transaction" : "facet English language-5",
    "sampleCount" : 622,
    "errorCount" : 0,
    "errorPct" : 0.0,
    "meanResTime" : 271.8392282958198,
    "minResTime" : 51.0,
    "maxResTime" : 2507.0,
    "pct1ResTime" : 456.2000000000003,
    "pct2ResTime" : 562.3500000000003,
    "pct3ResTime" : 1225.0299999999993,
    "throughput" : 0.7007858490831761,
    "receivedKBytesPerSec" : 7.729110260048446,
    "sentKBytesPerSec" : 0.4030887354589753
  },
  "Open search-11" : {
    "transaction" : "Open search-11",
    "sampleCount" : 630,
    "errorCount" : 0,
    "errorPct" : 0.0,
    "meanResTime" : 321.6158730158727,
    "minResTime" : 114.0,
    "maxResTime" : 1911.0,
    "pct1ResTime" : 476.69999999999993,
    "pct2ResTime" : 621.5999999999995,
    "pct3ResTime" : 1495.6899999999941,
    "throughput" : 0.7021783131670695,
    "receivedKBytesPerSec" : 29.131861137202858,
    "sentKBytesPerSec" : 0.4033998735521752
  },
  "facet English language-6" : {
    "transaction" : "facet English language-6",
    "sampleCount" : 622,
    "errorCount" : 0,
    "errorPct" : 0.0,
    "meanResTime" : 279.9871382636653,
    "minResTime" : 51.0,
    "maxResTime" : 3213.0,
    "pct1ResTime" : 482.80000000000064,
    "pct2ResTime" : 600.7,
    "pct3ResTime" : 1269.3299999999977,
    "throughput" : 0.7007605843577168,
    "receivedKBytesPerSec" : 7.948549838568758,
    "sentKBytesPerSec" : 0.4030742033073196
  },
  "Open search-10" : {
    "transaction" : "Open search-10",
    "sampleCount" : 630,
    "errorCount" : 0,
    "errorPct" : 0.0,
    "meanResTime" : 428.20793650793655,
    "minResTime" : 135.0,
    "maxResTime" : 2751.0,
    "pct1ResTime" : 661.0,
    "pct2ResTime" : 836.7999999999997,
    "pct3ResTime" : 1935.3899999999744,
    "throughput" : 0.7022205775151201,
    "receivedKBytesPerSec" : 31.488080336890324,
    "sentKBytesPerSec" : 0.4034241543257902
  },
  "facet English language-7" : {
    "transaction" : "facet English language-7",
    "sampleCount" : 622,
    "errorCount" : 0,
    "errorPct" : 0.0,
    "meanResTime" : 302.3504823151125,
    "minResTime" : 122.0,
    "maxResTime" : 2215.0,
    "pct1ResTime" : 499.70000000000005,
    "pct2ResTime" : 607.0,
    "pct3ResTime" : 1354.5899999999988,
    "throughput" : 0.7008458601080113,
    "receivedKBytesPerSec" : 8.935784716377144,
    "sentKBytesPerSec" : 0.4031232535191589
  },
  "facet English language-0" : {
    "transaction" : "facet English language-0",
    "sampleCount" : 622,
    "errorCount" : 0,
    "errorPct" : 0.0,
    "meanResTime" : 780.688102893891,
    "minResTime" : 328.0,
    "maxResTime" : 4111.0,
    "pct1ResTime" : 1046.8000000000002,
    "pct2ResTime" : 1177.65,
    "pct3ResTime" : 2308.4499999999985,
    "throughput" : 0.698258171416768,
    "receivedKBytesPerSec" : 45.18355079294961,
    "sentKBytesPerSec" : 0.43163810791681073
  },
  "facet English language-1" : {
    "transaction" : "facet English language-1",
    "sampleCount" : 622,
    "errorCount" : 0,
    "errorPct" : 0.0,
    "meanResTime" : 1403.0192926045013,
    "minResTime" : 141.0,
    "maxResTime" : 4309.0,
    "pct1ResTime" : 2042.3000000000004,
    "pct2ResTime" : 2325.4000000000005,
    "pct3ResTime" : 3063.77,
    "throughput" : 0.6995098932291491,
    "receivedKBytesPerSec" : 237.3200784572883,
    "sentKBytesPerSec" : 0.4385599135284314
  },
  "facet English language-2" : {
    "transaction" : "facet English language-2",
    "sampleCount" : 622,
    "errorCount" : 0,
    "errorPct" : 0.0,
    "meanResTime" : 3650.5353697749206,
    "minResTime" : 759.0,
    "maxResTime" : 7758.0,
    "pct1ResTime" : 4896.4,
    "pct2ResTime" : 5290.3,
    "pct3ResTime" : 6928.699999999998,
    "throughput" : 0.6981390441556109,
    "receivedKBytesPerSec" : 837.8041347569,
    "sentKBytesPerSec" : 0.437018679007565
  },
  "facet English language-3" : {
    "transaction" : "facet English language-3",
    "sampleCount" : 622,
    "errorCount" : 0,
    "errorPct" : 0.0,
    "meanResTime" : 230.55144694533755,
    "minResTime" : 25.0,
    "maxResTime" : 2655.0,
    "pct1ResTime" : 418.4000000000001,
    "pct2ResTime" : 539.9500000000002,
    "pct3ResTime" : 921.889999999999,
    "throughput" : 0.700777164128321,
    "receivedKBytesPerSec" : 0.6835737255319484,
    "sentKBytesPerSec" : 0.43730137488085663
  },
  "Total" : {
    "transaction" : "Total",
    "sampleCount" : 35714,
    "errorCount" : 8,
    "errorPct" : 0.02240018,
    "meanResTime" : 1043.0350282802283,
    "minResTime" : 0.0,
    "maxResTime" : 10747.0,
    "pct1ResTime" : 3720.9000000000015,
    "pct2ResTime" : 4510.9000000000015,
    "pct3ResTime" : 5749.960000000006,
    "throughput" : 39.542461588540945,
    "receivedKBytesPerSec" : 12023.479758409097,
    "sentKBytesPerSec" : 41.96843356633388
  },
  "Open search-13" : {
    "transaction" : "Open search-13",
    "sampleCount" : 630,
    "errorCount" : 0,
    "errorPct" : 0.0,
    "meanResTime" : 191.56825396825394,
    "minResTime" : 77.0,
    "maxResTime" : 1488.0,
    "pct1ResTime" : 266.9,
    "pct2ResTime" : 431.7499999999976,
    "pct3ResTime" : 1180.6799999999957,
    "throughput" : 0.7021861395143546,
    "receivedKBytesPerSec" : 14.819514825601484,
    "sentKBytesPerSec" : 0.40340436977122107
  },
  "Open search-12" : {
    "transaction" : "Open search-12",
    "sampleCount" : 630,
    "errorCount" : 0,
    "errorPct" : 0.0,
    "meanResTime" : 302.6142857142861,
    "minResTime" : 127.0,
    "maxResTime" : 3274.0,
    "pct1ResTime" : 462.69999999999993,
    "pct2ResTime" : 658.3499999999998,
    "pct3ResTime" : 1438.7699999999863,
    "throughput" : 0.7021626609958673,
    "receivedKBytesPerSec" : 28.906237156622957,
    "sentKBytesPerSec" : 0.4033908814147575
  }
}